run.py
marvel_characters/__init__.py
marvel_characters/functions.py
marvel_characters-0.1.dist-info/LICENSE
marvel_characters-0.1.dist-info/METADATA
marvel_characters-0.1.dist-info/WHEEL
marvel_characters-0.1.dist-info/top_level.txt
marvel_characters-0.1.dist-info/RECORD
